<workflow scriptid="customworkflow106">
  <description></description>
  <initcontexts>ACTION|BANKCONNECTIVITY|BANKSTATEMENTPARSER|BUNDLEINSTALLATION|CLIENT|CSVIMPORT|CUSTOMGLLINES|CUSTOMMASSUPDATE|RECORDACTION|DATASETBUILDER|DEBUGGER|EMAILCAPTURE|FICONNECTIVITY|FIPARSER|MAPREDUCE|OCRPLUGIN|OFFLINECLIENT|OTHER|PAYMENTPOSTBACK|PAYMENTGATEWAY|PLATFORMEXTENSION|PORTLET|PROMOTIONS|CONSOLRATEADJUSTOR|RESTWEBSERVICES|RESTLET|ADVANCEDREVREC|SCHEDULED|SDFINSTALLATION|SHIPPINGPARTNERS|WEBSERVICES|SUITELET|TAXCALCULATION|USEREVENT|USERINTERFACE|WORKBOOKBUILDER|WORKFLOW</initcontexts>
  <initeventtypes></initeventtypes>
  <initlocalizationcontext></initlocalizationcontext>
  <initoncreate>T</initoncreate>
  <initonvieworupdate>T</initonvieworupdate>
  <initsavedsearchcondition></initsavedsearchcondition>
  <inittriggertype></inittriggertype>
  <isinactive>F</isinactive>
  <islogenabled>T</islogenabled>
  <keephistory>ALWAYS</keephistory>
  <name>Created From Freeze</name>
  <recordtypes>[scriptid=custompurchase_srp_3pl_purchase_order]</recordtypes>
  <releasestatus>RELEASED</releasestatus>
  <runasadmin>T</runasadmin>
  <initcondition>
    <formula></formula>
    <type>VISUAL_BUILDER</type>
  </initcondition>
  <workflowstates>
    <workflowstate scriptid="workflowstate689">
      <description></description>
      <donotexitworkflow>F</donotexitworkflow>
      <name>State 1</name>
      <positionx>243</positionx>
      <positiony>133</positiony>
      <workflowactions triggertype="BEFORELOAD">
        <setdisplaytypeaction scriptid="workflowaction1217">
          <clienttriggerfields></clienttriggerfields>
          <conditionsavedsearch></conditionsavedsearch>
          <contexttypes>ACTION|BANKCONNECTIVITY|BANKSTATEMENTPARSER|BUNDLEINSTALLATION|CLIENT|CSVIMPORT|CUSTOMGLLINES|CUSTOMMASSUPDATE|RECORDACTION|DATASETBUILDER|DEBUGGER|EMAILCAPTURE|FICONNECTIVITY|FIPARSER|MAPREDUCE|OCRPLUGIN|OFFLINECLIENT|OTHER|PAYMENTPOSTBACK|PAYMENTGATEWAY|PLATFORMEXTENSION|PORTLET|PROMOTIONS|CONSOLRATEADJUSTOR|RESTWEBSERVICES|RESTLET|ADVANCEDREVREC|SCHEDULED|SDFINSTALLATION|SHIPPINGPARTNERS|WEBSERVICES|SUITELET|TAXCALCULATION|USEREVENT|USERINTERFACE|WORKBOOKBUILDER|WORKFLOW</contexttypes>
          <displaytype>DISABLED</displaytype>
          <eventtypes></eventtypes>
          <field>[scriptid=custbodycustbody158]</field>
          <isinactive>F</isinactive>
          <issublistfield>F</issublistfield>
          <initcondition>
            <formula></formula>
            <type>VISUAL_BUILDER</type>
          </initcondition>
        </setdisplaytypeaction>
        <setdisplaytypeaction scriptid="workflowaction1218">
          <clienttriggerfields></clienttriggerfields>
          <conditionsavedsearch></conditionsavedsearch>
          <contexttypes>ACTION|BANKCONNECTIVITY|BANKSTATEMENTPARSER|BUNDLEINSTALLATION|CLIENT|CSVIMPORT|CUSTOMGLLINES|CUSTOMMASSUPDATE|RECORDACTION|DATASETBUILDER|DEBUGGER|EMAILCAPTURE|FICONNECTIVITY|FIPARSER|MAPREDUCE|OCRPLUGIN|OFFLINECLIENT|OTHER|PAYMENTPOSTBACK|PAYMENTGATEWAY|PLATFORMEXTENSION|PORTLET|PROMOTIONS|CONSOLRATEADJUSTOR|RESTWEBSERVICES|RESTLET|ADVANCEDREVREC|SCHEDULED|SDFINSTALLATION|SHIPPINGPARTNERS|WEBSERVICES|SUITELET|TAXCALCULATION|USEREVENT|USERINTERFACE|WORKBOOKBUILDER|WORKFLOW</contexttypes>
          <displaytype>DISABLED</displaytype>
          <eventtypes></eventtypes>
          <field>STDBODYCREATEDFROM</field>
          <isinactive>F</isinactive>
          <issublistfield>F</issublistfield>
          <initcondition>
            <formula></formula>
            <type>VISUAL_BUILDER</type>
          </initcondition>
        </setdisplaytypeaction>
      </workflowactions>
    </workflowstate>
  </workflowstates>
</workflow>