<kpiscorecard scriptid="custkpiscorecard_atlas_production">
  <description>Scorecards are an intelligent tool allows users to monitor key information in real-time, from senior management down to the performance of teams and individuals. It consolidates information into useful information that gives users the big picture, enabling managers to make critical decisions at the right time.</description>
  <name>Production</name>
  <useperiods>F</useperiods>
  <custom>
    <kpi1>[scriptid=customsearch_atlas_wo_kpi]</kpi1>
    <kpi10></kpi10>
    <kpi2>[scriptid=customsearch_atlas_wo_planned_kpi]</kpi2>
    <kpi3>[scriptid=customsearch_atlas_wo_released_kpi]</kpi3>
    <kpi4>[scriptid=customsearch_atlas_wip_kpi]</kpi4>
    <kpi5>[scriptid=customsearch_atlas_wo_built_kpi]</kpi5>
    <kpi6>[scriptid=customsearch_atlas_wo_closed_kpi]</kpi6>
    <kpi7>[scriptid=customsearch_atlas_wo_cancel_kpi]</kpi7>
    <kpi8>[scriptid=customsearch_atlas_partial_built_kpi]</kpi8>
    <kpi9></kpi9>
  </custom>
  <audience>
    <allemployees>F</allemployees>
    <allpartners>F</allpartners>
    <allroles>T</allroles>
  </audience>
  <kpis>
    <kpi>
      <comparevalueto></comparevalueto>
      <comparewithprevious>F</comparewithprevious>
      <comparisontype></comparisontype>
      <hidden>F</hidden>
      <invertcomparison>F</invertcomparison>
      <kpi>CUSTOM</kpi>
      <label>Number of WOs</label>
    </kpi>
    <kpi>
      <comparevalueto></comparevalueto>
      <comparewithprevious>F</comparewithprevious>
      <comparisontype></comparisontype>
      <hidden>F</hidden>
      <invertcomparison>F</invertcomparison>
      <kpi>CUSTOM2</kpi>
      <label>Planned WOs</label>
    </kpi>
    <kpi>
      <comparevalueto></comparevalueto>
      <comparewithprevious>F</comparewithprevious>
      <comparisontype></comparisontype>
      <hidden>F</hidden>
      <invertcomparison>F</invertcomparison>
      <kpi>CUSTOM3</kpi>
      <label>Released WOs</label>
    </kpi>
    <kpi>
      <comparevalueto></comparevalueto>
      <comparewithprevious>F</comparewithprevious>
      <comparisontype></comparisontype>
      <hidden>F</hidden>
      <invertcomparison>F</invertcomparison>
      <kpi>CUSTOM8</kpi>
      <label>Partial Built WOs</label>
    </kpi>
    <kpi>
      <comparevalueto></comparevalueto>
      <comparewithprevious>F</comparewithprevious>
      <comparisontype></comparisontype>
      <hidden>F</hidden>
      <invertcomparison>F</invertcomparison>
      <kpi>CUSTOM5</kpi>
      <label>Built WOs</label>
    </kpi>
    <kpi>
      <comparevalueto></comparevalueto>
      <comparewithprevious>F</comparewithprevious>
      <comparisontype></comparisontype>
      <hidden>F</hidden>
      <invertcomparison>F</invertcomparison>
      <kpi>CUSTOM6</kpi>
      <label>Closed WOs</label>
    </kpi>
    <kpi>
      <comparevalueto></comparevalueto>
      <comparewithprevious>F</comparewithprevious>
      <comparisontype></comparisontype>
      <hidden>F</hidden>
      <invertcomparison>F</invertcomparison>
      <kpi>CUSTOM7</kpi>
      <label>Canceled WOs</label>
    </kpi>
  </kpis>
  <ranges>
    <range>
      <comparevalueto></comparevalueto>
      <comparewithprevious>F</comparewithprevious>
      <comparisontype></comparisontype>
      <invertcomparison>F</invertcomparison>
      <label>Today</label>
      <range>TODAY</range>
    </range>
    <range>
      <comparevalueto></comparevalueto>
      <comparewithprevious>F</comparewithprevious>
      <comparisontype></comparisontype>
      <invertcomparison>F</invertcomparison>
      <label>This Week</label>
      <range>THIS_WEEK</range>
    </range>
    <range>
      <comparevalueto></comparevalueto>
      <comparewithprevious>F</comparewithprevious>
      <comparisontype></comparisontype>
      <invertcomparison>F</invertcomparison>
      <label>This Month</label>
      <range>THIS_MONTH</range>
    </range>
    <range>
      <comparevalueto></comparevalueto>
      <comparewithprevious>F</comparewithprevious>
      <comparisontype></comparisontype>
      <invertcomparison>F</invertcomparison>
      <label>Last Month</label>
      <range>LAST_MONTH</range>
    </range>
    <range>
      <comparevalueto></comparevalueto>
      <comparewithprevious>F</comparewithprevious>
      <comparisontype></comparisontype>
      <invertcomparison>F</invertcomparison>
      <label>this fqtd</label>
      <range>THIS_FISCAL_QUARTER_TO_DATE</range>
    </range>
    <range>
      <comparevalueto></comparevalueto>
      <comparewithprevious>F</comparewithprevious>
      <comparisontype></comparisontype>
      <invertcomparison>F</invertcomparison>
      <label>last fqtd</label>
      <range>LAST_FISCAL_QUARTER_TO_DATE</range>
    </range>
    <range>
      <comparevalueto></comparevalueto>
      <comparewithprevious>F</comparewithprevious>
      <comparisontype></comparisontype>
      <invertcomparison>F</invertcomparison>
      <label>this fytd</label>
      <range>THIS_FISCAL_YEAR_TO_DATE</range>
    </range>
    <range>
      <comparevalueto></comparevalueto>
      <comparewithprevious>F</comparewithprevious>
      <comparisontype></comparisontype>
      <invertcomparison>F</invertcomparison>
      <label>last fytd</label>
      <range>LAST_FISCAL_YEAR_TO_DATE</range>
    </range>
  </ranges>
  <highlightings>
    <highlighting>
      <backgroundcolor></backgroundcolor>
      <bold>F</bold>
      <condition>ALWAYS</condition>
      <foregroundcolor></foregroundcolor>
      <headline>T</headline>
      <icon></icon>
      <kpiindex>1</kpiindex>
      <rangeindex>3</rangeindex>
      <threshold></threshold>
    </highlighting>
    <highlighting>
      <backgroundcolor>F1F1F1</backgroundcolor>
      <bold>F</bold>
      <condition>ALWAYS</condition>
      <foregroundcolor></foregroundcolor>
      <headline>F</headline>
      <icon></icon>
      <kpiindex>2</kpiindex>
      <rangeindex>ALL</rangeindex>
      <threshold></threshold>
    </highlighting>
    <highlighting>
      <backgroundcolor></backgroundcolor>
      <bold>F</bold>
      <condition>ALWAYS</condition>
      <foregroundcolor></foregroundcolor>
      <headline>F</headline>
      <icon></icon>
      <kpiindex>3</kpiindex>
      <rangeindex>ALL</rangeindex>
      <threshold></threshold>
    </highlighting>
    <highlighting>
      <backgroundcolor>F1F1F1</backgroundcolor>
      <bold>F</bold>
      <condition>ALWAYS</condition>
      <foregroundcolor></foregroundcolor>
      <headline>F</headline>
      <icon></icon>
      <kpiindex>4</kpiindex>
      <rangeindex>ALL</rangeindex>
      <threshold></threshold>
    </highlighting>
    <highlighting>
      <backgroundcolor></backgroundcolor>
      <bold>F</bold>
      <condition>ALWAYS</condition>
      <foregroundcolor></foregroundcolor>
      <headline>T</headline>
      <icon></icon>
      <kpiindex>5</kpiindex>
      <rangeindex>3</rangeindex>
      <threshold></threshold>
    </highlighting>
    <highlighting>
      <backgroundcolor>F1F1F1</backgroundcolor>
      <bold>F</bold>
      <condition>ALWAYS</condition>
      <foregroundcolor></foregroundcolor>
      <headline>F</headline>
      <icon></icon>
      <kpiindex>6</kpiindex>
      <rangeindex>ALL</rangeindex>
      <threshold></threshold>
    </highlighting>
    <highlighting>
      <backgroundcolor></backgroundcolor>
      <bold>F</bold>
      <condition>ALWAYS</condition>
      <foregroundcolor></foregroundcolor>
      <headline>F</headline>
      <icon></icon>
      <kpiindex>7</kpiindex>
      <rangeindex>ALL</rangeindex>
      <threshold></threshold>
    </highlighting>
    <highlighting>
      <backgroundcolor></backgroundcolor>
      <bold>F</bold>
      <condition>ALWAYS</condition>
      <foregroundcolor></foregroundcolor>
      <headline>T</headline>
      <icon></icon>
      <kpiindex>2</kpiindex>
      <rangeindex>3</rangeindex>
      <threshold></threshold>
    </highlighting>
    <highlighting>
      <backgroundcolor></backgroundcolor>
      <bold>F</bold>
      <condition>ALWAYS</condition>
      <foregroundcolor></foregroundcolor>
      <headline>T</headline>
      <icon></icon>
      <kpiindex>4</kpiindex>
      <rangeindex>3</rangeindex>
      <threshold></threshold>
    </highlighting>
  </highlightings>
</kpiscorecard>