<centercategory scriptid="custcentercategory47">
  <center>[scriptid=custcenter1]</center>
  <centertab>[scriptid=custcentertab13]</centertab>
  <label>Scheduling</label>
  <links>
    <link>
      <linkid>LIST_EVENT</linkid>
      <linklabel></linklabel>
      <shortlist>T</shortlist>
    </link>
    <link>
      <linkid>LIST_TASK</linkid>
      <linklabel></linklabel>
      <shortlist>T</shortlist>
    </link>
    <link>
      <linkid>LIST_CALL</linkid>
      <linklabel></linklabel>
      <shortlist>T</shortlist>
    </link>
    <link>
      <linkid>LIST_ACTIVITY</linkid>
      <linklabel>Activities</linklabel>
      <shortlist>T</shortlist>
    </link>
    <link>
      <linkid>LIST_PROJECTTASK</linkid>
      <linklabel></linklabel>
      <shortlist>T</shortlist>
    </link>
  </links>
</centercategory>