<kpiscorecard scriptid="kpiscorecard_3_t1195985_314">
  <description></description>
  <name>NetSuite Project Issues</name>
  <useperiods>F</useperiods>
  <custom>
    <kpi1>[scriptid=customsearch_ns_kpi_issues]</kpi1>
    <kpi10></kpi10>
    <kpi2>[scriptid=customsearch_ns_kpi_issues_2_2]</kpi2>
    <kpi3>[scriptid=customsearch_ns_kpi_issues_2_2_2_2]</kpi3>
    <kpi4>[scriptid=customsearch_ns_kpi_issues_2_2_2_2_2]</kpi4>
    <kpi5>[scriptid=customsearch_ns_kpi_issues_2_2_2]</kpi5>
    <kpi6>[scriptid=customsearch_ns_kpi_issues_2_2_2_2_3_2]</kpi6>
    <kpi7>[scriptid=customsearch_ns_kpi_issues_2_2_2_2_3_2_2]</kpi7>
    <kpi8>[scriptid=customsearch_ns_kpi_issues_2_2_2_2_3_2_3]</kpi8>
    <kpi9>[scriptid=customsearch_ns_kpi_issues_2_2_2_2_3]</kpi9>
  </custom>
  <audience>
    <allemployees>F</allemployees>
    <allpartners>F</allpartners>
    <allroles>F</allroles>
    <audslctrole>ADMINISTRATOR|[scriptid=customrole_ns_ps_implementation_team]|[scriptid=customrole1001_3]</audslctrole>
  </audience>
  <kpis>
    <kpi>
      <comparevalueto></comparevalueto>
      <comparewithprevious>F</comparewithprevious>
      <comparisontype></comparisontype>
      <hidden>F</hidden>
      <invertcomparison>F</invertcomparison>
      <kpi>CUSTOM</kpi>
      <label>Showstoppers</label>
    </kpi>
    <kpi>
      <comparevalueto></comparevalueto>
      <comparewithprevious>F</comparewithprevious>
      <comparisontype></comparisontype>
      <hidden>F</hidden>
      <invertcomparison>F</invertcomparison>
      <kpi>CUSTOM2</kpi>
      <label>Overdue</label>
    </kpi>
    <kpi>
      <formula>{CUSTOM3}+{CUSTOM4}+{CUSTOM5}+{CUSTOM6}+{CUSTOM7}+{CUSTOM8}</formula>
      <hidden>F</hidden>
      <kpi>FORMULANUMERIC</kpi>
      <label>Open</label>
      <lessismore>F</lessismore>
    </kpi>
    <kpi>
      <comparevalueto></comparevalueto>
      <comparewithprevious>F</comparewithprevious>
      <comparisontype></comparisontype>
      <hidden>F</hidden>
      <invertcomparison>F</invertcomparison>
      <kpi>CUSTOM3</kpi>
      <label>- Identified</label>
    </kpi>
    <kpi>
      <comparevalueto></comparevalueto>
      <comparewithprevious>F</comparewithprevious>
      <comparisontype></comparisontype>
      <hidden>F</hidden>
      <invertcomparison>F</invertcomparison>
      <kpi>CUSTOM4</kpi>
      <label>- In Process</label>
    </kpi>
    <kpi>
      <comparevalueto></comparevalueto>
      <comparewithprevious>F</comparewithprevious>
      <comparisontype></comparisontype>
      <hidden>F</hidden>
      <invertcomparison>F</invertcomparison>
      <kpi>CUSTOM5</kpi>
      <label>- With Support</label>
    </kpi>
    <kpi>
      <comparevalueto></comparevalueto>
      <comparewithprevious>F</comparewithprevious>
      <comparisontype></comparisontype>
      <hidden>F</hidden>
      <invertcomparison>F</invertcomparison>
      <kpi>CUSTOM6</kpi>
      <label>- Enhancement</label>
    </kpi>
    <kpi>
      <comparevalueto></comparevalueto>
      <comparewithprevious>F</comparewithprevious>
      <comparisontype></comparisontype>
      <hidden>F</hidden>
      <invertcomparison>F</invertcomparison>
      <kpi>CUSTOM7</kpi>
      <label>- On Hold</label>
    </kpi>
    <kpi>
      <comparevalueto></comparevalueto>
      <comparewithprevious>F</comparewithprevious>
      <comparisontype></comparisontype>
      <hidden>F</hidden>
      <invertcomparison>F</invertcomparison>
      <kpi>CUSTOM8</kpi>
      <label>- Future Phase</label>
    </kpi>
    <kpi>
      <comparevalueto></comparevalueto>
      <comparewithprevious>F</comparewithprevious>
      <comparisontype></comparisontype>
      <hidden>F</hidden>
      <invertcomparison>F</invertcomparison>
      <kpi>CUSTOM9</kpi>
      <label>Closed</label>
    </kpi>
  </kpis>
  <ranges>
    <range>
      <comparevalueto></comparevalueto>
      <comparewithprevious>F</comparewithprevious>
      <comparisontype></comparisontype>
      <invertcomparison>F</invertcomparison>
      <label></label>
      <range>TODAY</range>
    </range>
  </ranges>
  <highlightings>
    <highlighting>
      <backgroundcolor></backgroundcolor>
      <bold>T</bold>
      <condition>ALWAYS</condition>
      <foregroundcolor>ff0000</foregroundcolor>
      <headline>F</headline>
      <icon>EXCLAMATION_MARK</icon>
      <kpiindex>1</kpiindex>
      <rangeindex>ALL</rangeindex>
      <threshold></threshold>
    </highlighting>
    <highlighting>
      <backgroundcolor></backgroundcolor>
      <bold>T</bold>
      <condition>ALWAYS</condition>
      <foregroundcolor></foregroundcolor>
      <headline>F</headline>
      <icon></icon>
      <kpiindex>2</kpiindex>
      <rangeindex>ALL</rangeindex>
      <threshold></threshold>
    </highlighting>
    <highlighting>
      <backgroundcolor></backgroundcolor>
      <bold>T</bold>
      <condition>ALWAYS</condition>
      <foregroundcolor></foregroundcolor>
      <headline>F</headline>
      <icon></icon>
      <kpiindex>3</kpiindex>
      <rangeindex>ALL</rangeindex>
      <threshold></threshold>
    </highlighting>
    <highlighting>
      <backgroundcolor></backgroundcolor>
      <bold>F</bold>
      <condition>ALWAYS</condition>
      <foregroundcolor></foregroundcolor>
      <headline>F</headline>
      <icon></icon>
      <kpiindex>4</kpiindex>
      <rangeindex>ALL</rangeindex>
      <threshold></threshold>
    </highlighting>
    <highlighting>
      <backgroundcolor></backgroundcolor>
      <bold>F</bold>
      <condition>ALWAYS</condition>
      <foregroundcolor></foregroundcolor>
      <headline>F</headline>
      <icon></icon>
      <kpiindex>5</kpiindex>
      <rangeindex>ALL</rangeindex>
      <threshold></threshold>
    </highlighting>
    <highlighting>
      <backgroundcolor></backgroundcolor>
      <bold>F</bold>
      <condition>ALWAYS</condition>
      <foregroundcolor></foregroundcolor>
      <headline>F</headline>
      <icon></icon>
      <kpiindex>6</kpiindex>
      <rangeindex>ALL</rangeindex>
      <threshold></threshold>
    </highlighting>
    <highlighting>
      <backgroundcolor></backgroundcolor>
      <bold>F</bold>
      <condition>ALWAYS</condition>
      <foregroundcolor></foregroundcolor>
      <headline>F</headline>
      <icon></icon>
      <kpiindex>7</kpiindex>
      <rangeindex>ALL</rangeindex>
      <threshold></threshold>
    </highlighting>
    <highlighting>
      <backgroundcolor></backgroundcolor>
      <bold>F</bold>
      <condition>ALWAYS</condition>
      <foregroundcolor></foregroundcolor>
      <headline>F</headline>
      <icon></icon>
      <kpiindex>8</kpiindex>
      <rangeindex>ALL</rangeindex>
      <threshold></threshold>
    </highlighting>
    <highlighting>
      <backgroundcolor></backgroundcolor>
      <bold>F</bold>
      <condition>ALWAYS</condition>
      <foregroundcolor></foregroundcolor>
      <headline>F</headline>
      <icon></icon>
      <kpiindex>9</kpiindex>
      <rangeindex>ALL</rangeindex>
      <threshold></threshold>
    </highlighting>
    <highlighting>
      <backgroundcolor></backgroundcolor>
      <bold>T</bold>
      <condition>ALWAYS</condition>
      <foregroundcolor>008000</foregroundcolor>
      <headline>F</headline>
      <icon>CHECKMARK</icon>
      <kpiindex>10</kpiindex>
      <rangeindex>ALL</rangeindex>
      <threshold></threshold>
    </highlighting>
  </highlightings>
</kpiscorecard>